KataBankOCR-0.8.0.data/scripts/parse
KataBankOCR-0.8.0.dist-info/DESCRIPTION.rst
KataBankOCR-0.8.0.dist-info/METADATA
KataBankOCR-0.8.0.dist-info/pydist.json
KataBankOCR-0.8.0.dist-info/RECORD
KataBankOCR-0.8.0.dist-info/top_level.txt
KataBankOCR-0.8.0.dist-info/WHEEL
parse/__init__.py
parse/options.py
parse/parse
parse/settings.py
parse/validators.py
parse/version.py
parse/generators/__init__.py
parse/generators/accounts_from_superpositions.py
parse/generators/entries_from_path.py
parse/generators/figures_from_entries.py
parse/generators/results_from_accounts.py
parse/generators/superpositions_from_figures.py
parse/test/check_generator.py
parse/test/common_tools.py
parse/test/fixture_constants.py
parse/test/fixture_methods.py
parse/test/test_parse.py
parse/test/test_settings.py
parse/test/test_validators.py
parse/test/test_version.py
parse/test/input_files/advanced.txt
parse/test/input_files/basic.txt
parse/test/test_generators/test_accounts_from_superpositions.py
parse/test/test_generators/test_entries_from_path.py
parse/test/test_generators/test_figures_from_entries.py
parse/test/test_generators/test_results_from_accounts.py
parse/test/test_generators/test_superpositions_from_figures.py
